cnb/__init__.py
cnb/activities.py
cnb/ai.py
cnb/ai_ext.py
cnb/assets.py
cnb/badge.py
cnb/build.py
cnb/charge.py
cnb/client.py
cnb/cnb.py
cnb/event.py
cnb/exceptions.py
cnb/followers.py
cnb/git.py
cnb/gitsettings.py
cnb/issues.py
cnb/knowledgebase.py
cnb/members.py
cnb/missions.py
cnb/organizations.py
cnb/pulls.py
cnb/registries.py
cnb/releases.py
cnb/repocontributor.py
cnb/repolabels.py
cnb/repositories.py
cnb/security.py
cnb/starring.py
cnb/users.py
cnb/workspace.py
cnb/models/__init__.py
cnb/models/api.py
cnb/models/chart.py
cnb/models/constant.py
cnb/models/convert.py
cnb/models/die.py
cnb/models/dto.py
cnb/models/flags.py
cnb/models/git_woa_com_cnb_monorepo_git_internal_app_git_service_bff_api.py
cnb/models/git_woa_com_cnb_monorepo_git_internal_app_vcs_service_bff_api.py
cnb/models/models.py
cnb/models/openapi.py
cnb/models/organization.py
cnb/models/web.py
python_cnb-0.9.0.dist-info/licenses/LICENSE
python_cnb-0.9.0.dist-info/METADATA
python_cnb-0.9.0.dist-info/WHEEL
python_cnb-0.9.0.dist-info/top_level.txt
python_cnb-0.9.0.dist-info/RECORD
