Metadata-Version: 2.4
Name: python-cnb
Version: 0.9.0
Summary: CNB OpenAPI的Python SDK,方便与CNB平台进行交互
Home-page: https://cnb.cool
Author: Tencent Cloud
Author-email: ericdduan@tencent.com
License: MIT
Project-URL: Source, https://cnb.cool/cnb/sdk/python-cnb
Project-URL: Documentation, https://docs.cnb.cool
Classifier: Development Status :: 4 - Beta
Classifier: Intended Audience :: Developers
Classifier: License :: OSI Approved :: MIT License
Classifier: Programming Language :: Python :: 3.8
Classifier: Programming Language :: Python :: 3.9
Classifier: Programming Language :: Python :: 3.10
Classifier: Programming Language :: Python :: 3.11
Classifier: Topic :: Software Development :: Libraries :: Python Modules
Requires-Python: >=3.8
License-File: LICENSE
Requires-Dist: pydantic>=2.0.0
Requires-Dist: requests>=2.28.0
Requires-Dist: python-dotenv>=0.21.0
Dynamic: author
Dynamic: author-email
Dynamic: classifier
Dynamic: description
Dynamic: description-content-type
Dynamic: home-page
Dynamic: license
Dynamic: license-file
Dynamic: project-url
Dynamic: requires-dist
Dynamic: requires-python
Dynamic: summary
